MANIFEST.in
README.rst
setup.py
docs/HISTORY.txt
docs/LICENSE.GPL
docs/LICENSE.txt
ftw/__init__.py
ftw.blog.egg-info/PKG-INFO
ftw.blog.egg-info/SOURCES.txt
ftw.blog.egg-info/dependency_links.txt
ftw.blog.egg-info/entry_points.txt
ftw.blog.egg-info/namespace_packages.txt
ftw.blog.egg-info/not-zip-safe
ftw.blog.egg-info/requires.txt
ftw.blog.egg-info/top_level.txt
ftw/blog/__init__.py
ftw/blog/config.py
ftw/blog/configure.zcml
ftw/blog/eventhandlers.py
ftw/blog/hooks.py
ftw/blog/interfaces.py
ftw/blog/lawgiver.zcml
ftw/blog/testing.py
ftw/blog/tools.py
ftw/blog/utility.py
ftw/blog/zipexport.py
ftw/blog/Extensions/install.py
ftw/blog/browser/__init__.py
ftw/blog/browser/blog.pt
ftw/blog/browser/blog.py
ftw/blog/browser/blog.scss
ftw/blog/browser/configure.zcml
ftw/blog/browser/conversation.py
ftw/blog/browser/entry.pt
ftw/blog/browser/entry.py
ftw/blog/browser/rss.pt
ftw/blog/browser/rss.py
ftw/blog/browser/tabbed_blog_view.py
ftw/blog/browser/stylesheets/blog.css
ftw/blog/browser/widgets/__init__.py
ftw/blog/browser/widgets/category_widget.py
ftw/blog/content/__init__.py
ftw/blog/content/blog.py
ftw/blog/content/blogcategory.py
ftw/blog/content/blogentry.py
ftw/blog/content/configure.zcml
ftw/blog/latex/__init__.py
ftw/blog/latex/configure.zcml
ftw/blog/latex/layout.py
ftw/blog/latex/views.py
ftw/blog/latex/templates/blog.tex
ftw/blog/latex/templates/blog_layout.tex
ftw/blog/latex/templates/blogentry.tex
ftw/blog/locales/ftw.blog-manual.pot
ftw/blog/locales/ftw.blog.pot
ftw/blog/locales/ftw.tabbedview.pot
ftw/blog/locales/plone.pot
ftw/blog/locales/de/LC_MESSAGES/ftw.blog.po
ftw/blog/locales/de/LC_MESSAGES/ftw.tabbedview.po
ftw/blog/locales/de/LC_MESSAGES/plone.po
ftw/blog/locales/en/LC_MESSAGES/ftw.blog.po
ftw/blog/locales/en/LC_MESSAGES/ftw.tabbedview.po
ftw/blog/locales/en/LC_MESSAGES/plone.po
ftw/blog/locales/es/LC_MESSAGES/ftw.blog.po
ftw/blog/locales/es/LC_MESSAGES/plone.po
ftw/blog/locales/fr/LC_MESSAGES/ftw.blog.po
ftw/blog/locales/fr/LC_MESSAGES/ftw.tabbedview.po
ftw/blog/locales/fr/LC_MESSAGES/plone.po
ftw/blog/portlets/__init__.py
ftw/blog/portlets/archiv.pt
ftw/blog/portlets/archiv.py
ftw/blog/portlets/blogentry_collection_portlet.pt
ftw/blog/portlets/blogentry_collection_portlet.py
ftw/blog/portlets/categories.pt
