Metadata-Version: 2.1
Name: ftw.blog
Version: 1.8.1
Summary: A Blog for Plone
Home-page: https://github.com/4teamwork/ftw.blog
Author: 4teamwork AG
Author-email: mailto:info@4teamwork.ch
Maintainer: Mathias Leimgruber
License: GPL2
Keywords: ftw blog
Platform: UNKNOWN
Classifier: Framework :: Plone
Classifier: Framework :: Zope2
Classifier: Framework :: Plone :: 4.2
Classifier: Framework :: Plone :: 4.3
Classifier: Programming Language :: Python
Classifier: Topic :: Software Development :: Libraries :: Python Modules
Provides-Extra: zip_export
Provides-Extra: tests
Provides-Extra: tabbeview
